<xml xmlns:o="urn:schemas-microsoft-com:office:office">
 <o:MainFile HRef="../gsasII-phase.html"/>
 <o:File HRef="item0060.xml"/>
 <o:File HRef="props061.xml"/>
 <o:File HRef="themedata.thmx"/>
 <o:File HRef="colorschememapping.xml"/>
 <o:File HRef="image055.emz"/>
 <o:File HRef="image056.png"/>
 <o:File HRef="image057.emz"/>
 <o:File HRef="image058.png"/>
 <o:File HRef="image059.emz"/>
 <o:File HRef="image060.png"/>
 <o:File HRef="image061.emz"/>
 <o:File HRef="image062.png"/>
 <o:File HRef="image063.emz"/>
 <o:File HRef="image064.emz"/>
 <o:File HRef="image065.png"/>
 <o:File HRef="image066.emz"/>
 <o:File HRef="image067.png"/>
 <o:File HRef="image068.emz"/>
 <o:File HRef="image069.png"/>
 <o:File HRef="image070.emz"/>
 <o:File HRef="image071.png"/>
 <o:File HRef="image072.emz"/>
 <o:File HRef="image073.png"/>
 <o:File HRef="image074.emz"/>
 <o:File HRef="image075.png"/>
 <o:File HRef="image076.emz"/>
 <o:File HRef="image077.emz"/>
 <o:File HRef="image078.png"/>
 <o:File HRef="image079.emz"/>
 <o:File HRef="image080.png"/>
 <o:File HRef="image081.emz"/>
 <o:File HRef="image082.png"/>
 <o:File HRef="image083.emz"/>
 <o:File HRef="image084.png"/>
 <o:File HRef="image085.emz"/>
 <o:File HRef="image086.png"/>
 <o:File HRef="image087.emz"/>
 <o:File HRef="image088.png"/>
 <o:File HRef="image089.emz"/>
 <o:File HRef="image090.png"/>
 <o:File HRef="image091.emz"/>
 <o:File HRef="image092.png"/>
 <o:File HRef="image093.emz"/>
 <o:File HRef="image094.png"/>
 <o:File HRef="image095.emz"/>
 <o:File HRef="image096.png"/>
 <o:File HRef="image097.emz"/>
 <o:File HRef="image098.emz"/>
 <o:File HRef="image099.png"/>
 <o:File HRef="image100.emz"/>
 <o:File HRef="image101.png"/>
 <o:File HRef="image102.emz"/>
 <o:File HRef="image103.png"/>
 <o:File HRef="image104.emz"/>
 <o:File HRef="image105.emz"/>
 <o:File HRef="image106.png"/>
 <o:File HRef="filelist.xml"/>
</xml>